niconico_translator.py
niconico_translator-0.1.5.dist-info/DESCRIPTION.rst
niconico_translator-0.1.5.dist-info/METADATA
niconico_translator-0.1.5.dist-info/RECORD
niconico_translator-0.1.5.dist-info/WHEEL
niconico_translator-0.1.5.dist-info/entry_points.txt
niconico_translator-0.1.5.dist-info/metadata.json
niconico_translator-0.1.5.dist-info/top_level.txt
