Metadata-Version: 2.0
Name: niconico-translator
Version: 0.1.5
Summary: Translating comments on Nico Nico Douga (ニコニコ動画).
Home-page: https://bitbucket.org/dahlia/niconico-translator
Author: Hong Minhee
Author-email: minhee@dahlia.kr
License: AGPLv3
Download-URL: https://bitbucket.org/dahlia/niconico-translator/downloads
Platform: UNKNOWN
Classifier: Development Status :: 3 - Alpha
Classifier: Environment :: Web Environment
Classifier: Intended Audience :: Developers
Classifier: Intended Audience :: End Users/Desktop
Classifier: Natural Language :: Japanese
Classifier: License :: OSI Approved :: GNU Affero General Public License v3
Classifier: Operating System :: OS Independent
Classifier: Programming Language :: Python :: 3.2
Classifier: Programming Language :: Python :: 3.3
Classifier: Programming Language :: Python :: Implementation :: CPython
Classifier: Programming Language :: Python :: Implementation :: Stackless
Classifier: Topic :: Internet :: WWW/HTTP :: Dynamic Content :: Message Boards
Classifier: Topic :: Internet :: WWW/HTTP :: WSGI :: Application
Classifier: Topic :: Multimedia :: Sound/Audio :: Players
Requires-Dist: WebOb (>=1.2.1)
Requires-Dist: dnspython3 (>=1.11.0)
Requires-Dist: html5lib (>=1.0b1)
Requires-Dist: lxml (>=3.2.0)
Requires-Dist: requests (>=1.2.0)
Requires-Dist: waitress (>=0.8)
